libspn/__init__.py
libspn/conf.py
libspn/exceptions.py
libspn/log.py
libspn/examples/__init__.py
libspn/examples/convspn/__init__.py
libspn/examples/convspn/amsgrad.py
libspn/examples/convspn/architecture.py
libspn/examples/convspn/collage.py
libspn/examples/convspn/reproduce_icml_submission.py
libspn/examples/convspn/train.py
libspn/examples/convspn/utils.py
libspn/examples/utils/__init__.py
libspn/examples/utils/dataiterator.py
libspn/generation/__init__.py
libspn/generation/conversion.py
libspn/generation/dense.py
libspn/generation/weights.py
libspn/graph/__init__.py
libspn/graph/algorithms.py
libspn/graph/distribution.py
libspn/graph/loader.py
libspn/graph/node.py
libspn/graph/saver.py
libspn/graph/scope.py
libspn/graph/serialization.py
libspn/graph/weights.py
libspn/graph/leaf/__init__.py
libspn/graph/leaf/cauchy.py
libspn/graph/leaf/continuous_base.py
libspn/graph/leaf/indicator.py
libspn/graph/leaf/laplace.py
libspn/graph/leaf/location_scale.py
libspn/graph/leaf/multivariate_cauchy_diag.py
libspn/graph/leaf/multivariate_normal_diag.py
libspn/graph/leaf/normal.py
libspn/graph/leaf/raw.py
libspn/graph/leaf/student_t.py
libspn/graph/leaf/truncated_normal.py
libspn/graph/op/__init__.py
libspn/graph/op/base_sum.py
libspn/graph/op/block_merge_decompositions.py
libspn/graph/op/block_permute_product.py
libspn/graph/op/block_random_decompositions.py
libspn/graph/op/block_random_decompositions_v2.py
libspn/graph/op/block_reduce_product.py
libspn/graph/op/block_root_sum.py
libspn/graph/op/block_root_sum_v2.py
libspn/graph/op/block_sum.py
libspn/graph/op/concat.py
libspn/graph/op/conv_products.py
libspn/graph/op/conv_products_depthwise.py
libspn/graph/op/conv_sums.py
libspn/graph/op/local_sums.py
libspn/graph/op/parallel_sums.py
libspn/graph/op/permute_products.py
libspn/graph/op/product.py
libspn/graph/op/products_layer.py
libspn/graph/op/spatial_sums.py
libspn/graph/op/sum.py
libspn/graph/op/sumslayer.py
libspn/inference/__init__.py
libspn/inference/mpe_path.py
libspn-0.1.3.dist-info/LICENSE
libspn-0.1.3.dist-info/METADATA
libspn-0.1.3.dist-info/WHEEL
libspn-0.1.3.dist-info/top_level.txt
libspn-0.1.3.dist-info/RECORD
