Metadata-Version: 2.1
Name: libspn
Version: 0.1.3
Summary: LibSPN is a TensorFlow-based library for building and training Sum-Product Networks.
Home-page: http://www.libspn.org
Author: Andrzej Pronobis, Avinash Raganath, Jos van de Wolfshaar
Author-email: a.pronobis@gmail.com
License: MIT
Keywords: libspn spn deep-learning deep-learning-library machine-learning machine-learning-library tensorflow
Platform: UNKNOWN
Classifier: Development Status :: 4 - Beta
Classifier: Programming Language :: Python :: 3
Classifier: Programming Language :: Python :: 3.4
Classifier: Programming Language :: Python :: 3.5
Classifier: Programming Language :: Python :: 3.6
Classifier: Programming Language :: Python :: 3.7
Classifier: Intended Audience :: Developers
Classifier: Intended Audience :: Education
Classifier: Intended Audience :: Science/Research
Classifier: Topic :: Scientific/Engineering :: Artificial Intelligence
Classifier: Topic :: Scientific/Engineering :: Mathematics
Classifier: Topic :: Software Development :: Libraries :: Python Modules
Classifier: Topic :: Software Development :: Libraries
Classifier: License :: OSI Approved :: MIT License
Requires-Dist: tqdm
Requires-Dist: numpy
Requires-Dist: scipy
Requires-Dist: matplotlib
Requires-Dist: pillow
Requires-Dist: pyyaml
